recongraph/__init__.py
recongraph/recongraph.py
recongraph-0.0.1.dist-info/licenses/LICENSE
recongraph-0.0.1.dist-info/METADATA
recongraph-0.0.1.dist-info/WHEEL
recongraph-0.0.1.dist-info/entry_points.txt
recongraph-0.0.1.dist-info/top_level.txt
recongraph-0.0.1.dist-info/RECORD
