Metadata-Version: 2.4
Name: recongraph
Version: 0.0.1
Summary: Reconstruction of Forensic Timelines Using Graph Theory
Author: Muhammad Nur Yasir Utomo
Project-URL: Homepage, https://github.com/forensic-timeline/recongraph
Classifier: Programming Language :: Python :: 3
Classifier: Operating System :: OS Independent
Requires-Python: >=3.8
License-File: LICENSE
Requires-Dist: PyYAML
Requires-Dist: networkx
Requires-Dist: pandas
Requires-Dist: lxml
Dynamic: license-file
